LICENSE
MANIFEST.in
README.md
pyproject.toml
requirements.txt
setup.cfg
setup.py
chatgpthub/__init__.py
chatgpthub/generate.py
chatgpthub.egg-info/PKG-INFO
chatgpthub.egg-info/SOURCES.txt
chatgpthub.egg-info/dependency_links.txt
chatgpthub.egg-info/requires.txt
chatgpthub.egg-info/top_level.txt
chatgpthub/templates/__init__.py
chatgpthub/templates/create_template.py
chatgpthub/templates/csv_template.py
chatgpthub/templates/translate_template.py
chatgpthub/tools/__init__.py
chatgpthub/tools/prompt_layer.py
chatgpthub/utils/__init__.py
chatgpthub/utils/key_utils.py