Metadata-Version: 2.1
Name: chatgpthub
Version: 0.1.2
Summary: ChatGptHub: Gpt Chatbot Library with LangChain Support
Home-page: https://github.com/kadirnar/chatgpthub
Author: kadirnar
License: Apache-2.0
Keywords: chatgpt,chatbot,gpt-3,gpt-3.5-turbo,text-generation,language-model,language-modeling
Classifier: Development Status :: 5 - Production/Stable
Classifier: Operating System :: OS Independent
Classifier: Intended Audience :: Developers
Classifier: Intended Audience :: Science/Research
Classifier: Programming Language :: Python :: 3
Classifier: Programming Language :: Python :: 3.7
Classifier: Programming Language :: Python :: 3.8
Classifier: Programming Language :: Python :: 3.9
Classifier: Topic :: Software Development :: Libraries
Classifier: Topic :: Software Development :: Libraries :: Python Modules
Classifier: Topic :: Education
Classifier: Topic :: Scientific/Engineering
Classifier: Topic :: Scientific/Engineering :: Artificial Intelligence
Requires-Python: >=3.6
License-File: LICENSE
